django_channels_utils/__init__.py
django_channels_utils/script.py
django_channels_utils/abstract_consumer/__init__.py
django_channels_utils/abstract_consumer/abstract_consumer.py
django_channels_utils/abstract_consumer/abstract_consumer_errors.py
django_channels_utils/abstract_consumer/const.py
django_channels_utils/abstract_consumer_handler/__init__.py
django_channels_utils/abstract_consumer_handler/abstract_consumer_handler.py
django_channels_utils/abstract_consumer_handler/abstract_consumer_handler_errors.py
django_channels_utils/abstract_consumer_handler/const.py
django_channels_utils/utils/__init__.py
django_channels_utils/utils/abstract_custom_error.py
tests/__init__.py
tests/test_abstract_consumer_handler.py
django_channels_utils-0.2.2.dist-info/LICENSE
django_channels_utils-0.2.2.dist-info/METADATA
django_channels_utils-0.2.2.dist-info/WHEEL
django_channels_utils-0.2.2.dist-info/entry_points.txt
django_channels_utils-0.2.2.dist-info/top_level.txt
django_channels_utils-0.2.2.dist-info/RECORD
