Metadata-Version: 2.1
Name: django-channels-utils
Version: 0.2.2
Summary: This is a package to improve django-channels functionality
Home-page: https://github.com/cds88/django-channels-utils
Author: setsudo
Author-email: sergiusz.cudo@outlook.com
License: UNKNOWN
Platform: UNKNOWN
Classifier: Programming Language :: Python :: 3
Classifier: License :: OSI Approved :: MIT License
Classifier: Operating System :: OS Independent
Requires-Python: >3.6
License-File: LICENSE
Requires-Dist: django-channels
